playaudio/__init__.py
playaudio/api.py
playaudio/cli.py
playaudio/assets/__init__.py
playaudio/assets/bell.mp3
playaudio/assets/builtin.py
playaudio-1.0.5.dist-info/LICENSE
playaudio-1.0.5.dist-info/METADATA
playaudio-1.0.5.dist-info/WHEEL
playaudio-1.0.5.dist-info/entry_points.txt
playaudio-1.0.5.dist-info/top_level.txt
playaudio-1.0.5.dist-info/RECORD
