Metadata-Version: 2.1
Name: playaudio
Version: 1.0.5
Summary: Plays audio files on Windows/MacOS/Linux
Home-page: https://github.com/zackees/playaudio
License: BSD 3-Clause License
Keywords: playaudio,audio,sound
Classifier: Programming Language :: Python :: 3
Requires-Python: >=3.7
License-File: LICENSE
Requires-Dist: pygame ; sys_platform == "win32"
